{
    "code": "1",
    "data":[
        {
            "title":"系统通知",
            "time":"2015-02-21 22:22:11",
            "content":"回收打印机墨盒的消费者还可以获得奖励积分，用于以后购买史泰博的商品"
        },
        {
            "title":"系统通知",
            "time":"2015-02-21 22:22:11",
            "content":"回收打印机墨盒的消费者还可以获得奖励积分，用于以后购买史泰博的商品"
        },
        {
            "title":"系统通知",
            "time":"2015-02-21 22:22:11",
            "content":"回收打印机墨盒的消费者还可以获得奖励积分，用于以后购买史泰博的商品"
        },
        {
            "title":"系统通知",
            "time":"2015-02-21 22:22:11",
            "content":"回收打印机墨盒的消费者还可以获得奖励积分，用于以后购买史泰博的商品"
        },
        {
            "title":"系统通知",
            "time":"2015-02-21 22:22:11",
            "content":"回收打印机墨盒的消费者还可以获得奖励积分，用于以后购买史泰博的商品"
        },
        {
            "title":"系统通知",
            "time":"2015-02-21 22:22:11",
            "content":"回收打印机墨盒的消费者还可以获得奖励积分，用于以后购买史泰博的商品"
        },
        {
            "title":"系统通知",
            "time":"2015-02-21 22:22:11",
            "content":"回收打印机墨盒的消费者还可以获得奖励积分，用于以后购买史泰博的商品"
        }
    ]
}
